elv/__init__.py
elv/elv.py
elv-1.0.14.dist-info/DESCRIPTION.rst
elv-1.0.14.dist-info/METADATA
elv-1.0.14.dist-info/metadata.json
elv-1.0.14.dist-info/RECORD
elv-1.0.14.dist-info/top_level.txt
elv-1.0.14.dist-info/WHEEL
elv-1.0.14.dist-info/zip-safe
