Metadata-Version: 2.0
Name: elv
Version: 1.0.14
Summary: Parser and query API for bank CSV account transactions
Home-page: https://github.com/cslarsen/elv
Author: Christian Stigen Larsen
Author-email: csl@csl.name
License: https://www.gnu.org/licenses/agpl-3.0.html
Download-URL: https://github.com/cslarsen/elv/tarball/1.0.14
Keywords: bank,csv,transaction,transactions,money,sparebank,finance
Platform: unix
Platform: linux
Platform: osx
Platform: cygwin
Platform: win32
Classifier: Development Status :: 3 - Alpha
Classifier: Environment :: Console
Classifier: Natural Language :: English
Classifier: Operating System :: MacOS :: MacOS X
Classifier: Operating System :: Microsoft :: Windows
Classifier: Operating System :: POSIX
Classifier: Operating System :: Unix
Classifier: Programming Language :: Python
Classifier: Programming Language :: Python :: 2
Classifier: Programming Language :: Python :: 2.6
Classifier: Programming Language :: Python :: 2.7
Classifier: Programming Language :: Python :: 3
Classifier: Programming Language :: Python :: 3.1
Classifier: Programming Language :: Python :: 3.2
Classifier: Programming Language :: Python :: 3.3
Classifier: Programming Language :: Python :: Implementation :: PyPy
